flake8_datetime_import.py
flake8_datetime_import-0.1.0.dist-info/LICENSE
flake8_datetime_import-0.1.0.dist-info/METADATA
flake8_datetime_import-0.1.0.dist-info/WHEEL
flake8_datetime_import-0.1.0.dist-info/entry_points.txt
flake8_datetime_import-0.1.0.dist-info/top_level.txt
flake8_datetime_import-0.1.0.dist-info/RECORD
