Metadata-Version: 2.1
Name: flake8-datetime-import
Version: 0.1.0
Summary: A plugin for flake8 which enforces importing `datetime as dt` and `time as tm`.
Author-email: Marc Gibbons <marc@marcgibbons.com>
License: MIT
Project-URL: Homepage, https://github.com/marcgibbons/flake8-datetime-import
Keywords: flake8,datetime,time,qa
Classifier: Development Status :: 5 - Production/Stable
Classifier: Environment :: Console
Classifier: Framework :: Flake8
Classifier: Intended Audience :: Developers
Classifier: License :: OSI Approved :: MIT License
Classifier: Operating System :: OS Independent
Classifier: Programming Language :: Python
Classifier: Programming Language :: Python :: 3
Classifier: Programming Language :: Python :: 3.7
Classifier: Programming Language :: Python :: 3.8
Classifier: Programming Language :: Python :: 3.9
Classifier: Programming Language :: Python :: 3.10
Classifier: Programming Language :: Python :: 3.11
Classifier: Programming Language :: Python :: 3 :: Only
Classifier: Topic :: Software Development :: Libraries :: Python Modules
Classifier: Topic :: Software Development :: Quality Assurance
Requires-Python: >=3.7
License-File: LICENSE
Requires-Dist: importlib-metadata (>=0.9) ; python_version < "3.8"
Provides-Extra: build
Requires-Dist: build ; extra == 'build'
Provides-Extra: dev
Requires-Dist: tox ; extra == 'dev'
Requires-Dist: pre-commit ; extra == 'dev'
Provides-Extra: gh
Requires-Dist: tox-gh ; extra == 'gh'
